txtlocal
