Metadata-Version: 1.0
Name: django-txtlocal
Version: 1.1.3
Summary: App for sending and receiving SMS messages via http://www.textlocal.com
Home-page: https://github.com/incuna/django-txtlocal/
Author: Incuna Ltd
Author-email: admin@incuna.com
License: UNKNOWN
Platform: UNKNOWN
